DFAnalyzer/__init__.py
DFAnalyzer/hello.py
dfanalyzer-0.0.4.dist-info/METADATA
dfanalyzer-0.0.4.dist-info/WHEEL
dfanalyzer-0.0.4.dist-info/top_level.txt
dfanalyzer-0.0.4.dist-info/RECORD
