Metadata-Version: 2.1
Name: dfanalyzer
Version: 0.0.4
Summary: Pyspark Dataframe Analyzer - Smartest DataFrame Analysis
Author: Neetish Singh(AAYS Anaytics)
Author-email: <neetishsingh97@gmail.com>
Keywords: python,pyspark,spark,ingestion,data,dataframe,analysis,schema,pandas
Classifier: Development Status :: 1 - Planning
Classifier: Intended Audience :: Developers
Classifier: Programming Language :: Python :: 3
Classifier: Operating System :: Unix
Classifier: Operating System :: MacOS :: MacOS X
Classifier: Operating System :: Microsoft :: Windows
